multi_indexer/__init__.py
multi_indexer/main.py
multi_indexer-0.0.5.dist-info/LICENSE
multi_indexer-0.0.5.dist-info/METADATA
multi_indexer-0.0.5.dist-info/WHEEL
multi_indexer-0.0.5.dist-info/entry_points.txt
multi_indexer-0.0.5.dist-info/index.html
multi_indexer-0.0.5.dist-info/top_level.txt
multi_indexer-0.0.5.dist-info/RECORD
