Metadata-Version: 2.1
Name: multi-indexer
Version: 0.0.5
Summary: A utility for creating sets of templated indexes for local or remote directories.
Home-page: https://github.com/Knowledge-Graph-Hub/multi-indexer
Author: Harry Caufield
Author-email: 
License: BSD-3
Platform: UNKNOWN
Requires-Python: >=3.7
License-File: LICENSE
Requires-Dist: boto3
Requires-Dist: pystache
Provides-Extra: test
Requires-Dist: pytest ; extra == 'test'
Requires-Dist: pytest-cov ; extra == 'test'
Requires-Dist: coveralls ; extra == 'test'
Requires-Dist: validate-version-code ; extra == 'test'
Requires-Dist: codacy-coverage ; extra == 'test'
Requires-Dist: parameterized ; extra == 'test'
